hello_world/__init__.py
hello_world_eyad123-0.1.dist-info/METADATA
hello_world_eyad123-0.1.dist-info/WHEEL
hello_world_eyad123-0.1.dist-info/top_level.txt
hello_world_eyad123-0.1.dist-info/RECORD
