Metadata-Version: 2.4
Name: hello-world-eyad123
Version: 0.1
Summary: My hello world package
Author: Eyad
Author-email: eyadseif17@outlook.com
Requires-Python: >=3.6
Dynamic: author
Dynamic: author-email
Dynamic: requires-python
Dynamic: summary
